{
    "generationMode":  "mixed_avatar_ai_video",
    "modeName":  "混合数字人与 AI 视频",
    "createdAt":  "2026-06-23T14:12:03",
    "providers":  {
                      "tts":  "windows_system_speech_or_external_tts",
                      "text":  "configured_or_local_fallback",
                      "avatar":  "pending",
                      "voiceClone":  "pending",
                      "aiVideo":  "pending",
                      "composer":  "ffmpeg_optional"
                  },
    "renderStrategy":  "Generate AI video scenes as background, overlay avatar video, then mix voice and subtitles.",
    "options":  {
                    "generationMode":  "mixed_avatar_ai_video",
                    "style":  "知识口播",
                    "ratio":  "9:16",
                    "resolution":  "720p",
                    "fps":  30,
                    "voice":  {
                                  "type":  "system",
                                  "rate":  0,
                                  "volume":  100
                              }
                },
    "segments":  [
                     {
                         "index":  1,
                         "duration":  27,
                         "sceneMode":  "avatar_overlay_ai_scene",
                         "voiceText":  "人工智能正在改变内容生产方式。过去制作一条完整视频通常需要文案、配音、拍摄、剪辑和后期多个环节配合完成。现在，通过文本理解、语音合成、数字人口播和 AI 视频生成，可以把一篇普通文稿快速转换成可发布的视频内容。",
                         "subtitle":  "人工智能正在改变内容生产方式。过去制作一条完整视频通常需要文案、配音、拍摄、剪辑和后期多个环节配合完成。现在，通过文本理解、语音合成、数字人口播和 AI 视频生成，可以把一篇普通文稿快速转换成可发布的视频内容。",
                         "visualPrompt":  "围绕以下内容生成画面：人工智能正在改变内容生产方式。过去制作一条完整视频通常需要文案、配音、拍摄、剪辑和后期多个环节配合完成。现在，通过文本理解、语音合成、数字人",
                         "requiredAssets":  [
                                                "voice_audio",
                                                "avatar_alpha_video",
                                                "ai_video_scene",
                                                "subtitle",
                                                "background_music"
                                            ],
                         "status":  "pending_provider_integration"
                     },
                     {
                         "index":  2,
                         "duration":  27,
                         "sceneMode":  "avatar_overlay_ai_scene",
                         "voiceText":  "本工具的目标是把这些步骤整合到本地电脑中。用户只需要导入一个 txt 文件，系统就能生成口播脚本、配音音频、字幕文件和视频合成配置。后续接入数字人和 AI 视频接口后，还可以进一步自动生成完整的数字人口播视频。",
                         "subtitle":  "本工具的目标是把这些步骤整合到本地电脑中。用户只需要导入一个 txt 文件，系统就能生成口播脚本、配音音频、字幕文件和视频合成配置。后续接入数字人和 AI 视频接口后，还可以进一步自动生成完整的数字人口播视频。",
                         "visualPrompt":  "围绕以下内容生成画面：本工具的目标是把这些步骤整合到本地电脑中。用户只需要导入一个 txt 文件，系统就能生成口播脚本、配音音频、字幕文件和视频合成配置。后续接入",
                         "requiredAssets":  [
                                                "voice_audio",
                                                "avatar_alpha_video",
                                                "ai_video_scene",
                                                "subtitle",
                                                "background_music"
                                            ],
                         "status":  "pending_provider_integration"
                     }
                 ]
}
